{
  "project_info": {
    "project_number": "1015160786723",
    "firebase_url": "https://temp-hh.firebaseio.com",
    "project_id": "temp-hh",
    "storage_bucket": "temp-hh.appspot.com"
  },
  "client": [
    {
      "client_info": {
        "mobilesdk_app_id": "1:1015160786723:android:4734b267be052fb9",
        "android_client_info": {
          "package_name": "com.example.ryanchan.handoffhelper"
        }
      },
      "oauth_client": [
        {
          "client_id": "1015160786723-vdggg9siv3rt30qr7l5g0r945q9585nf.apps.googleusercontent.com",
          "client_type": 3
        }
      ],
      "api_key": [
        {
          "current_key": "AIzaSyDsuMPu8y2QFG-8YuAoHQw16vUHblcitNQ"
        }
      ],
      "services": {
        "analytics_service": {
          "status": 1
        },
        "appinvite_service": {
          "status": 1,
          "other_platform_oauth_client": []
        },
        "ads_service": {
          "status": 2
        }
      }
    }
  ],
  "configuration_version": "1"
}